AUTHORS.md
COPYING
MANIFEST.in
README.rst
pypump-shell
setup.py
PyPump.egg-info/PKG-INFO
PyPump.egg-info/SOURCES.txt
PyPump.egg-info/dependency_links.txt
PyPump.egg-info/requires.txt
PyPump.egg-info/top_level.txt
docs/Makefile
docs/classref.rst
docs/conf.py
docs/index.rst
docs/store.rst
docs/_build/doctrees/classref.doctree
docs/_build/doctrees/environment.pickle
docs/_build/doctrees/index.doctree
docs/_build/doctrees/store.doctree
docs/_build/doctrees/common/media.doctree
docs/_build/doctrees/gettingstarted/authentication.doctree
docs/_build/doctrees/gettingstarted/installing.doctree
docs/_build/doctrees/gettingstarted/qnd.doctree
docs/_build/doctrees/gettingstarted/tutorial.doctree
docs/_build/doctrees/gettingstarted/verifier_callback.doctree
docs/_build/doctrees/gettingstarted/webpump.doctree
docs/_build/doctrees/models/activity.doctree
docs/_build/doctrees/models/comment.doctree
docs/_build/doctrees/models/image.doctree
docs/_build/doctrees/models/inbox.doctree
docs/_build/doctrees/models/note.doctree
docs/_build/doctrees/models/person.doctree
docs/_build/html/.buildinfo
docs/_build/html/classref.html
docs/_build/html/genindex.html
docs/_build/html/index.html
docs/_build/html/objects.inv
docs/_build/html/search.html
docs/_build/html/searchindex.js
docs/_build/html/store.html
docs/_build/html/_modules/index.html
docs/_build/html/_modules/pypump/client.html
docs/_build/html/_modules/pypump/models.html
docs/_build/html/_modules/pypump/pypump.html
docs/_build/html/_modules/pypump/models/collection.html
docs/_build/html/_modules/pypump/models/comment.html
docs/_build/html/_modules/pypump/models/feed.html
docs/_build/html/_modules/pypump/models/image.html
docs/_build/html/_modules/pypump/models/note.html
docs/_build/html/_modules/pypump/models/person.html
docs/_build/html/_sources/classref.txt
docs/_build/html/_sources/index.txt
docs/_build/html/_sources/store.txt
docs/_build/html/_sources/common/media.txt
docs/_build/html/_sources/gettingstarted/authentication.txt
docs/_build/html/_sources/gettingstarted/installing.txt
docs/_build/html/_sources/gettingstarted/qnd.txt
