Metadata-Version: 1.1
Name: PyPump
Version: 0.6
Summary: Python Pump.io library
Home-page: https://github.com/xray7224/PyPump
Author: Jessica Tallon
Author-email: tfmyz@inboxen.org
License: GPLv3+
Platform: UNKNOWN
Classifier: Development Status :: 3 - Alpha
Classifier: Programming Language :: Python
Classifier: Programming Language :: Python :: 2
Classifier: Programming Language :: Python :: 2.6
Classifier: Programming Language :: Python :: 2.7
Classifier: Programming Language :: Python :: 3
Classifier: Programming Language :: Python :: 3.3
Classifier: Programming Language :: Python :: Implementation :: CPython
Classifier: Operating System :: OS Independent
Classifier: Operating System :: POSIX
Classifier: Operating System :: Microsoft :: Windows
Classifier: Operating System :: MacOS :: MacOS X
Classifier: Intended Audience :: Developers
Classifier: License :: OSI Approved
Classifier: License :: OSI Approved :: GNU General Public License v3 (GPLv3)
Classifier: License :: OSI Approved :: GNU General Public License v3 or later (GPLv3+)
